surrealdb/__init__.py
surrealdb/_surrealdb_ext.abi3.so
surrealdb/_surrealdb_ext.pyi
surrealdb/cbor/__init__.py
surrealdb/cbor/_decoder.py
surrealdb/cbor/_encoder.py
surrealdb/cbor/_types.py
surrealdb/cbor/decoder.py
surrealdb/cbor/encoder.py
surrealdb/cbor/py.typed
surrealdb/cbor/tool.py
surrealdb/cbor/types.py
surrealdb/connections/__init__.py
surrealdb/connections/async_embedded.py
surrealdb/connections/async_http.py
surrealdb/connections/async_template.py
surrealdb/connections/async_ws.py
surrealdb/connections/blocking_embedded.py
surrealdb/connections/blocking_http.py
surrealdb/connections/blocking_ws.py
surrealdb/connections/mixins/__init__.py
surrealdb/connections/sync_template.py
surrealdb/connections/url.py
surrealdb/connections/utils_mixin.py
surrealdb/data/README.md
surrealdb/data/__init__.py
surrealdb/data/cbor.py
surrealdb/data/models.py
surrealdb/data/types/__init__.py
surrealdb/data/types/constants.py
surrealdb/data/types/datetime.py
surrealdb/data/types/duration.py
surrealdb/data/types/geometry.py
surrealdb/data/types/range.py
surrealdb/data/types/record_id.py
surrealdb/data/types/table.py
surrealdb/data/utils.py
surrealdb/errors.py
surrealdb/py.typed
surrealdb/request_message/__init__.py
surrealdb/request_message/descriptors/__init__.py
surrealdb/request_message/descriptors/cbor_ws.py
surrealdb/request_message/message.py
surrealdb/request_message/methods.py
surrealdb/request_message/sql_adapter.py
surrealdb/types.py
surrealdb-1.0.8.dist-info/METADATA
surrealdb-1.0.8.dist-info/WHEEL
surrealdb-1.0.8.dist-info/licenses/LICENSE
surrealdb-1.0.8.dist-info/RECORD
