Metadata-Version: 2.4
Name: surrealdb
Version: 1.0.8
Classifier: Development Status :: 5 - Production/Stable
Classifier: Intended Audience :: Developers
Classifier: Operating System :: OS Independent
Classifier: Programming Language :: Python :: 3
Classifier: Programming Language :: Python :: 3.9
Classifier: Programming Language :: Python :: 3.10
Classifier: Programming Language :: Python :: 3.11
Classifier: Programming Language :: Python :: 3.12
Classifier: Programming Language :: Python :: 3.13
Classifier: Topic :: Database
Classifier: Topic :: Database :: Front-Ends
Classifier: Topic :: Database :: Database Engines/Servers
Classifier: Topic :: Software Development
Classifier: Topic :: Software Development :: Libraries :: Python Modules
Requires-Dist: aiohttp>=3.8.0
Requires-Dist: pydantic-core>=2.0.1
Requires-Dist: requests>=2.25.0
Requires-Dist: typing-extensions>=4.0.0 ; python_full_version < '3.12'
Requires-Dist: websockets>=10.0
Requires-Dist: pydantic>=2.12.5 ; extra == 'pydantic'
Provides-Extra: pydantic
License-File: LICENSE
Summary: SurrealDB python client
Keywords: SurrealDB,Database
Author: SurrealDB
License-Expression: Apache-2.0
Requires-Python: >=3.9
Project-URL: documentation, https://surrealdb.com/docs/sdk/python
Project-URL: homepage, https://github.com/surrealdb/surrealdb.py
Project-URL: repository, https://github.com/surrealdb/surrealdb.py
